dynamicdl/__init__.py
dynamicdl/_utils.py
dynamicdl/_warnings.py
dynamicdl/config.py
dynamicdl/dynamicdl.py
dynamicdl/dynamicds.py
dynamicdl/_main/__init__.py
dynamicdl/_main/_collate.py
dynamicdl/_main/_engine.py
dynamicdl/_main/_transforms.py
dynamicdl/_main/_utils.py
dynamicdl/data/__init__.py
dynamicdl/data/dataentry.py
dynamicdl/data/dataitem.py
dynamicdl/data/datatype.py
dynamicdl/data/datatypes.py
dynamicdl/data/partialtype.py
dynamicdl/data/tokens.py
dynamicdl/parsing/__init__.py
dynamicdl/parsing/alias.py
dynamicdl/parsing/ambiguouslist.py
dynamicdl/parsing/generic.py
dynamicdl/parsing/genericlist.py
dynamicdl/parsing/impliedlist.py
dynamicdl/parsing/namespace.py
dynamicdl/parsing/pairing.py
dynamicdl/parsing/segmentationobject.py
dynamicdl/parsing/static.py
dynamicdl/processing/__init__.py
dynamicdl/processing/csvfile.py
dynamicdl/processing/datafile.py
dynamicdl/processing/images.py
dynamicdl/processing/jsonfile.py
dynamicdl/processing/txtfile.py
dynamicdl/processing/xmlfile.py
dynamicdl/processing/yamlfile.py
dynamicdl-0.1.1a0.dist-info/LICENSE
dynamicdl-0.1.1a0.dist-info/METADATA
dynamicdl-0.1.1a0.dist-info/WHEEL
dynamicdl-0.1.1a0.dist-info/top_level.txt
dynamicdl-0.1.1a0.dist-info/RECORD
